phylomito/__init__.py
phylomito/mt_download.py
phylomito/phylomito.py
phylomito/taxonomy_parser.py
phylomito/data/mitochondria_tree
phylomito/data/organism_taxid
phylomito/data/taxid_to_filenames
phylomito-0.1.0.dist-info/LICENCE
phylomito-0.1.0.dist-info/METADATA
phylomito-0.1.0.dist-info/WHEEL
phylomito-0.1.0.dist-info/entry_points.txt
phylomito-0.1.0.dist-info/top_level.txt
phylomito-0.1.0.dist-info/RECORD
