Metadata-Version: 2.1
Name: phylomito
Version: 0.1.0
Summary: Supermatrix phylogenetics using complete mitochondrial genomes
Home-page: https://github.com/igorrcosta/phylomito
Author: Igor Rodrigues da Costa
Author-email: igor.bioinfo@gmail.com
License: UNKNOWN
Platform: UNKNOWN
Classifier: Programming Language :: Python :: 3
Classifier: License :: OSI Approved :: GNU General Public License v3 (GPLv3)
Classifier: Operating System :: OS Independent
Classifier: Topic :: Scientific/Engineering :: Bio-Informatics
License-File: LICENCE
Requires-Dist: biopython
Requires-Dist: anytree
